fppclient/__init__.py
fppclient/cli/__init__.py
fppclient/cli/async_typer.py
fppclient/const.py
fppclient/endpoints.json
fppclient/endpoints_fppd.json
fppclient/endpoints_system.json
fppclient/exceptions.py
fppclient/fpp.py
fppclient/models.py
fppclient/py.typed
fppclient/utils.py
fppclient-0.1.0.dist-info/LICENSE
fppclient-0.1.0.dist-info/METADATA
fppclient-0.1.0.dist-info/WHEEL
fppclient-0.1.0.dist-info/entry_points.txt
fppclient-0.1.0.dist-info/RECORD
